gitlab_cloner/__init__.py
gitlab_cloner/gitlab_api.py
gitlab_cloner-1.1.0.data/scripts/gitlab-cloner
gitlab_cloner-1.1.0.dist-info/METADATA
gitlab_cloner-1.1.0.dist-info/RECORD
gitlab_cloner-1.1.0.dist-info/WHEEL
gitlab_cloner-1.1.0.dist-info/top_level.txt
test/__init__.py
test/test_cloning.py
