Metadata-Version: 2.1
Name: gitlab-cloner
Version: 1.1.0
Summary: A script that can batch-clone all repositories of a gitlab user
Home-page: https://gitlab.namibsun.net/namibsun/python/gitlab-cloner
Author: Hermann Krumrey
Author-email: hermann@krumreyh.com
License: GNU GPL3
Platform: UNKNOWN
Classifier: License :: OSI Approved :: GNU General Public License v3 (GPLv3)
Requires-Dist: requests
Requires-Dist: colorama
Requires-Dist: typing
